{
    "settings" :
    {
        "websiteTitle"  : "##customer_name##",
        "dateFormat"    : "d.m.Y",
        "datimFormat"   : "d.m.Y H:i",
        "timeZone"      : "Europe/Vienna",
        "adminEmail"    : "##admin_email##",
        "minifyMarkup"  : true,
        "gzipScripts"   : true,
        "folderUrl"     : true,
        "maxFileSize"   : "5242880",
        "imageWidth"    : "1600",
        "imageHeight"   : "1600",

        "defaultUser"   : "##editor_user_id###",
        "defaultGroup"  : "##editor_group_id##",
        "defaultChmod"  : ["u1", "u2", "u3", "u4", "u5", "u6", "g1", "g2", "g4", "g5", "g6"]
    },

    "templates" : ["global", "website"],

    "files" :
    {
        "master"    : ["css", "js", "images"],
        "website"   : ["css", "images", "Uploads"]
    },

    "pages" :
    {
        "rootPage"  :
        {
            "title"         : "##customer_name##",
            "alias"         : "##customer_alias",
            "language"      : "de",
            "type"          : "root",
            "fallback"      : true,
            "includeLayout" : true,
            "layout"        : "##layout_id##",
            "published"     : true,

            "subpages"      :
            {
                "homepage" :
                {
                    "title"         : "Startseite",
                    "alais"         : "startseite",
                    "type"          : "regular",
                    "pid"           : "##page_rootPage_id##",
                    "cssClass"      : "homepage",
                    "published"     : true
                },

                "globalElements" :
                {
                    "title"         : "Global Elements",
                    "alais"         : "global-elements",
                    "type"          : "regular",
                    "pid"           : "##page_rootPage_id##",
                    "hide"          : true,
                    "published"     : true
                }
            }
        }
    },

    "articles" :
    {
        "startseite" :
        {
            "title"         : "Startseite",
            "alias"         : "startseite",
            "author"        : "##admin_user_id##",
            "pid"           : "##page_homepage_id##",
            "inColumn"      : "main",
            "published"     : true
        },

        "globalElements_header" :
        {
            "title"         : "Kopfzeile",
            "alais"         : "se_header_##customer_alias##_de",
            "author"        : "##admin_user_id##",
            "pid"           : "##page_globalElements_id##",
            "inColumn"      : "main",
            "published"     : true
        },

        "globalElements_footer" :
        {
            "title"         : "Fußzeile",
            "alais"         : "se_footer_##customer_alias##_de",
            "author"        : "##admin_user_id##",
            "pid"           : "##page_globalElements_id##",
            "inColumn"      : "main",
            "published"     : true
        }
    },

    "user" :
    {
        "name"      : "##customer_name##",
        "email"     : "#customer_email##",
        "username"  : "user",
        "password"  : "u1234567",
        "pwChange"  : true
    },

    "user_group" :
    {
        "name"          : "Redakteur",
        "modules"       : ["article", "page", "files"],
        "pagemounts"    : "##page_rootPage_id##",
        "alpty"         : ["regular", "forward", "redirect"],
        "filemounts"    : "##files_website/Uploads##",
        "fop"           : ["f1", "f2", "f3"],
        "alexf"         :
        [
            "tl_article::title",
            "tl_article::alias",
            "tl_article::author",
            "tl_article::inColumn",
            "tl_article::cssID",
            "tl_article::published",
            "tl_article::start",
            "tl_article::stop",

            "tl_content::type",
            "tl_content::headline",
            "tl_content::text",
            "tl_content::addImage",
            "tl_content::singleSRC",
            "tl_content::alt",
            "tl_content::size",
            "tl_content::imagemargin",
            "tl_content::imageUrl",
            "tl_content::fullsize",
            "tl_content::floating",
            "tl_content::url",
            "tl_content::target",
            "tl_content::titleText",
            "tl_content::linkTitle",
            "tl_content::rel",
            "tl_content::multiSRC",
            "tl_content::numberOfItems",
            "tl_content::sortBy",
            "tl_content::galleryTpl",
            "tl_content::cteAlias",
            "tl_content::articleAlias",
            "tl_content::article",
            "tl_content::form",
            "tl_content::module",
            "tl_content::cssID",
            "tl_content::invisible",
            "tl_content::start",
            "tl_content::stop",
            "tl_content::rsce_data",

            "tl_page::title",
            "tl_page::alias",
            "tl_page::type",
            "tl_page::pageTitle",
            "tl_page::language",
            "tl_page::description",
            "tl_page::redirect",
            "tl_page::jumpTo",
            "tl_page::url",
            "tl_page::target",
            "tl_page::dns",
            "tl_page::fallback",
            "tl_page::includeLayout",
            "tl_page::layout",
            "tl_page::cssClass",
            "tl_page::hide",
            "tl_page::published",
            "tl_page::start",
            "tl_page::stop",

            "tl_news_archive::title",
            "tl_news_archive::jumpTo",

            "tl_news::headline",
            "tl_news::alias",
            "tl_news::author",
            "tl_news::date",
            "tl_news::time",
            "tl_news::subheadline",
            "tl_news::teaser",
            "tl_news::addImage",
            "tl_news::singleSRC",
            "tl_news::size",
            "tl_news::alt",
            "tl_news::imagemargin",
            "tl_news::imageUrl",
            "tl_news::fullsize",
            "tl_news::floating",
            "tl_news::source",
            "tl_news::jumpTo",
            "tl_news::articleId",
            "tl_news::url",
            "tl_news::target",
            "tl_news::cssClass",
            "tl_news::featured",
            "tl_news::published",
            "tl_news::start",
            "tl_news::stop",

            "tl_calendar::title",
            "tl_calendar::jumpTo",

            "tl_calendar_events::title",
            "tl_calendar_events::alias",
            "tl_calendar_events::author",
            "tl_calendar_events::addTime",
            "tl_calendar_events::startTime",
            "tl_calendar_events::endTime",
            "tl_calendar_events::startDate",
            "tl_calendar_events::endDate",
            "tl_calendar_events::location",
            "tl_calendar_events::teaser",
            "tl_calendar_events::addImage",
            "tl_calendar_events::singleSRC",
            "tl_calendar_events::alt",
            "tl_calendar_events::size",
            "tl_calendar_events::imagemargin",
            "tl_calendar_events::imageUrl",
            "tl_calendar_events::fullsize",
            "tl_calendar_events::floating",
            "tl_calendar_events::recurring",
            "tl_calendar_events::repeatEach",
            "tl_calendar_events::recurring",
            "tl_calendar_events::repeatEach",
            "tl_calendar_events::recurrences",
            "tl_calendar_events::source",
            "tl_calendar_events::jumpTo",
            "tl_calendar_events::articleId",
            "tl_calendar_events::url",
            "tl_calendar_events::target",
            "tl_calendar_events::cssClass",
            "tl_calendar_events::published",
            "tl_calendar_events::start",
            "tl_calendar_events::stop"
        ]
    }
}